{
  "ts": "2026-06-16T17:04:25Z",
  "post": {
    "url": "https://old.reddit.com/r/PLC/comments/1u7i0bo/4_weeks_as_automation_engineer_advice_on_plc_programmring/",
    "title": "4 Weeks as Automation Engineer - Advice on PLC Programmring?",
    "subreddit": "PLC"
  },
  "replies_posted": [
    {
      "target_comment_url": "https://old.reddit.com/r/PLC/comments/1u7i0bo/4_weeks_as_automation_engineer_advice_on_plc/os0g4kk/",
      "target_author": "u/PLCGoBrrr",
      "reply_url": "https://old.reddit.com/r/PLC/comments/1u7i0bo/4_weeks_as_automation_engineer_advice_on_plc/os0p2sn/",
      "reply_text": "Two things that paid off for me beyond the generic advice. Install TwinCAT XAE free on a Windows laptop and run it in dev mode at home, you get the full Beckhoff IDE plus a free runtime for development which means a virtual PLC instance for experimentation without touching production. Then learn the PLCopen Motion Control FB names since Beckhoff and Siemens both implement the spec, state diagrams and parameter patterns carry across vendors which is huge when you bounce between projects."
    }
  ],
  "followups_posted": [],
  "followups_skipped": [],
  "skip_reason": null,
  "personality": "casual-realist"
}
