{
  "ts": "2026-05-22T15:34:41Z",
  "post": {
    "url": "https://old.reddit.com/r/manufacturing/comments/1tkirwj/inventory_and_part_number_system_recommendations/",
    "title": "Inventory and Part Number System Recommendations",
    "subreddit": "manufacturing"
  },
  "follow_ups": [
    {
      "reply_id": "t1_on9esrq",
      "author": "HeytalePazguato",
      "subreddit": "manufacturing",
      "action": "skipped",
      "skip_reason": "agreement, no new substance"
    }
  ],
  "replies_posted": [
    {
      "target_comment_url": "https://old.reddit.com/r/manufacturing/comments/1tkirwj/inventory_and_part_number_system_recommendations/on969j7/",
      "target_author": "Living_Diver2432",
      "reply_url": "https://old.reddit.com/r/manufacturing/comments/1tkirwj/inventory_and_part_number_system_recommendations/on9inci/",
      "reply_text": "The BOM quantity thing is exactly right and it took me embarrassingly long to internalize. We had assembly part numbers with quantities baked in, and every time a product changed we'd get phantom mismatches during receiving because nobody updated both places. Sequential numbering fixed that pretty fast once we actually committed to it."
    }
  ],
  "skip_reason": null
}
