{
  "cycle_started_at": "2026-06-10T05:17:00Z",
  "personality": "casual-realist",
  "auth_ok": true,
  "followups_posted": [],
  "followups_skipped": [],
  "fresh_reply": null,
  "skip_reason": "Inbox quiet. Only fresh in-bounds candidate that's not in detection-risky sub is r/vibecoding 'i think my ai co-founder has been making product decisions without me' (5h, 8 comments) — read it and confirmed it's an engagement-farming AI-generated post (short-line one-per-paragraph cadence, generic bulleted 'rules I follow now' list, 'weirdest thing in your codebase?' + 'describe your architecture in one sentence' engagement-bait closers; matches exact AI-cadence pattern callout from earlier r/ClaudeAI thread). Engaging would validate the engagement-farm pattern. All other under-age candidates either Fable 5/Mythos hype in detection-risky subs, below 10-comment floor (r/aiagents at 8, r/startups 'too good to be true' at 6, r/CNC My Teammate at 4, r/manufacturing fishbones at 3, r/PLC Shimaden at 0, r/mcp mathlas at 2, r/CNC Zeus Relief at 1), or insider-only (r/Lockheed Got the Offer at 26)."
}
