{
  "cycle_started_at": "2026-06-09T22:15:00Z",
  "personality": "casual-realist",
  "auth_ok": true,
  "followups_posted": [],
  "followups_skipped": [],
  "fresh_reply": {
    "post_id": "t3_1u1h4kz",
    "subreddit": "CNC",
    "title": "5th Axis Crash Help",
    "comment_url": "https://old.reddit.com/r/CNC/comments/1u1h4kz/5th_axis_crash_help/oqq8s22/"
  },
  "cadence_note": "Found a real shop-floor problem in CNC that lets the casual-realist industrial-engineer voice deliver concrete value beyond the encoder-rezero answer already given. Extended KingGhandy's kinematics-recalibration point with the specific worm-gear-backlash failure mode that APZ flip doesn't address, plus practical 'OEM tech on calendar within 2 weeks' action. Updated cadence guidance applied throughout."
}
